pybind11_geobuf/__init__.py
pybind11_geobuf/__main__.py
pybind11_geobuf/_core/__init__.pyi
pybind11_geobuf/_core/geojson.pyi
pybind11_geobuf/_core/tf.pyi
pybind11_geobuf/_core.cp312-win_amd64.pyd
pybind11_geobuf/crop.py
pybind11_geobuf/geobuf2json.exe
pybind11_geobuf/json2geobuf.exe
pybind11_geobuf/lintjson.exe
pybind11_geobuf/normalize_json.exe
pybind11_geobuf/pbf_decoder.exe
pybind11_geobuf/py.typed
pybind11_geobuf/sample.exe
pybind11_geobuf/test_geobuf.exe
pybind11_geobuf-0.2.4.dist-info/METADATA
pybind11_geobuf-0.2.4.dist-info/WHEEL
pybind11_geobuf-0.2.4.dist-info/licenses/LICENSE
pybind11_geobuf-0.2.4.dist-info/RECORD
