Metadata-Version: 2.2
Name: pybind11_geobuf
Version: 0.2.4
Summary: c++ geobuf with python binding
Author-Email: district10 <dvorak4tzx@gmail.com>
Classifier: Development Status :: 4 - Beta
Classifier: License :: OSI Approved :: MIT License
Classifier: Programming Language :: Python :: 3 :: Only
Classifier: Programming Language :: Python :: 3.7
Classifier: Programming Language :: Python :: 3.8
Classifier: Programming Language :: Python :: 3.9
Classifier: Programming Language :: Python :: 3.10
Classifier: Programming Language :: Python :: 3.11
Classifier: Programming Language :: Python :: 3.12
Classifier: Programming Language :: Python :: 3.13
Classifier: Programming Language :: Python :: 3.14
Project-URL: Homepage, https://geobuf-cpp.readthedocs.io
Requires-Python: >=3.7
Requires-Dist: fire
Requires-Dist: loguru
Requires-Dist: numpy
Provides-Extra: test
Requires-Dist: pytest; extra == "test"
